4.1/LED41_blink.v
module LED_blink (
    input wire CLK,
    input wire SW2,
    output wire LED0, LED1, LED2, LED3, LED4, LED5, LED6, LED7
);
    // Declaración de señales
    reg [27:0] data = 0;
    
    // Asignación: bit 24 de data se asigna a la salida LED
    assign LED0 = data[0];
    assign LED1 = data[1];
    assign LED2 = data[2];
    assign LED3 = data[3];
    assign LED4 = data[4];
    assign LED5 = data[5];
    assign LED6 = data[6];
    assign LED7 = data[7];
    
    // Contador: incrementa con cada flanco de subida del reloj
    always @(posedge CLK)
        begin
            if (SW2)  //Si SW2 está pulsado, reiniciar el contador
                data <= 0;
            else    // De lo contrario, incrementa el contador normalmente
                data <= data + 1;
        end
endmodule

4.1/LED41_blink_tb.v
`timescale 1ns/100ps

module testbench ();
    reg clk = 0;
    reg button = 0;
    wire led0, led1, led2, led3, led4, led5, led6, led7;

    // Generamos reloj
    // Periodo = 5 * timescale = 5 * 1ns
    localparam CLOCK_PERIOD = 5;

    // Inicialmente está a 0
    initial clk = 1'b0;

    // Cambio valor de clk cada 5ns
    always #CLOCK_PERIOD clk = ~clk;

    // INICIALIZO BOTON
    initial begin
        button = 0;
        #500;    // 5ms
        button = 1;
        #500;    // 5ms
        button = 0;

    end

    reg errores = 0;

    // Instancia del módulo LED_blink
    LED_blink DUT (
        .CLK(clk),
        .SW2(button),  
        .LED0(led0),
        .LED1(led1),
        .LED2(led2),
        .LED3(led3),
        .LED4(led4),
        .LED5(led5),
        .LED6(led6),
        .LED7(led7)
    );

    // Verificar el comportamiento esperado
    initial begin
        $dumpfile(`DUMPSTR("LED41_blink_tb.vcd"));
        $dumpvars(0, testbench);
        #1;
        if (!(led0 === 0 && led1 === 0 && led2 === 0 && led3 === 0 && led4 === 0 && led5 === 0 && led6 === 0 && led7 === 0))
        begin
            $display("Error: LEDs no están en 0 al inicio");
            errores = errores + 1;
        end
        // Comprobación después de pulsar el boton
        #505;
        // Comprobar si los LEDs son los esperados después del reset
        if (!(led0 === 0 && led1 === 0 && led2 === 0 && led3 === 0 && led4 === 0 && led5 === 0 && led6 === 0 && led7 === 0))
        begin
            $display("Error: Configuración de LEDs incorrecta después del reset");
            errores = errores + 1;
        end
        #500;
        // Comprobar si los LEDs son los esperados después de soltar el boton
        if (!(led0 === 1 && led1 === 0 && led2 === 0 && led3 === 0 && led4 === 0 && led5 === 0 && led6 === 0 && led7 === 0))
        begin
            $display("Error: Configuración de LEDs incorrecta después de soltar el boton");
            errores = errores + 1;
        end

        if (errores === 0)
            $display("\nTestbench completado sin errores\n");
        else
            $display("\nTestbench completado con %d errores\n", errores);
        #500;

        $finish;
    end
endmodule

4.1/LED41_blink_tb.vcd
$date
	Fri Dec 29 18:36:03 2023
$end
$version
	Icarus Verilog
$end
$timescale
	1ps
$end
$scope module testbench $end
$var wire 1 ! led7 $end
$var wire 1 " led6 $end
$var wire 1 # led5 $end
$var wire 1 $ led4 $end
$var wire 1 % led3 $end
$var wire 1 & led2 $end
$var wire 1 ' led1 $end
$var wire 1 ( led0 $end
$var reg 1 ) button $end
$var reg 1 * clk $end
$var reg 1 + errores $end
$scope module DUT $end
$var wire 1 * CLK $end
$var wire 1 ) SW2 $end
$var wire 1 ! LED7 $end
$var wire 1 " LED6 $end
$var wire 1 # LED5 $end
$var wire 1 $ LED4 $end
$var wire 1 % LED3 $end
$var wire 1 & LED2 $end
$var wire 1 ' LED1 $end
$var wire 1 ( LED0 $end
$var reg 28 , data [27:0] $end
$upscope $end
$upscope $end
$enddefinitions $end
#0
$dumpvars
b0 ,
0+
0*
0)
0(
0'
0&
0%
0$
0#
0"
0!
$end
#5000
1(
b1 ,
1*
#10000
0*
#15000
0(
1'
b10 ,
1*
#20000
0*
#25000
1(
b11 ,
1*
#30000
0*
#35000
0(
0'
1&
b100 ,
1*
#40000
0*
#45000
1(
b101 ,
1*
#50000
0*
#55000
0(
1'
b110 ,
1*
#60000
0*
#65000
1(
b111 ,
1*
#70000
0*
#75000
0(
0'
0&
1%
b1000 ,
1*
#80000
0*
#85000
1(
b1001 ,
1*
#90000
0*
#95000
0(
1'
b1010 ,
1*
#100000
0*
#105000
1(
b1011 ,
1*
#110000
0*
#115000
0(
0'
1&
b1100 ,
1*
#120000
0*
#125000
1(
b1101 ,
1*
#130000
0*
#135000
0(
1'
b1110 ,
1*
#140000
0*
#145000
1(
b1111 ,
1*
#150000
0*
#155000
0(
0'
0&
0%
1$
b10000 ,
1*
#160000
0*
#165000
1(
b10001 ,
1*
#170000
0*
#175000
0(
1'
b10010 ,
1*
#180000
0*
#185000
1(
b10011 ,
1*
#190000
0*
#195000
0(
0'
1&
b10100 ,
1*
#200000
0*
#205000
1(
b10101 ,
1*
#210000
0*
#215000
0(
1'
b10110 ,
1*
#220000
0*
#225000
1(
b10111 ,
1*
#230000
0*
#235000
0(
0'
0&
1%
b11000 ,
1*
#240000
0*
#245000
1(
b11001 ,
1*
#250000
0*
#255000
0(
1'
b11010 ,
1*
#260000
0*
#265000
1(
b11011 ,
1*
#270000
0*
#275000
0(
0'
1&
b11100 ,
1*
#280000
0*
#285000
1(
b11101 ,
1*
#290000
0*
#295000
0(
1'
b11110 ,
1*
#300000
0*
#305000
1(
b11111 ,
1*
#310000
0*
#315000
0(
0'
0&
0%
0$
1#
b100000 ,
1*
#320000
0*
#325000
1(
b100001 ,
1*
#330000
0*
#335000
0(
1'
b100010 ,
1*
#340000
0*
#345000
1(
b100011 ,
1*
#350000
0*
#355000
0(
0'
1&
b100100 ,
1*
#360000
0*
#365000
1(
b100101 ,
1*
#370000
0*
#375000
0(
1'
b100110 ,
1*
#380000
0*
#385000
1(
b100111 ,
1*
#390000
0*
#395000
0(
0'
0&
1%
b101000 ,
1*
#400000
0*
#405000
1(
b101001 ,
1*
#410000
0*
#415000
0(
1'
b101010 ,
1*
#420000
0*
#425000
1(
b101011 ,
1*
#430000
0*
#435000
0(
0'
1&
b101100 ,
1*
#440000
0*
#445000
1(
b101101 ,
1*
#450000
0*
#455000
0(
1'
b101110 ,
1*
#460000
0*
#465000
1(
b101111 ,
1*
#470000
0*
#475000
0(
0'
0&
0%
1$
b110000 ,
1*
#480000
0*
#485000
1(
b110001 ,
1*
#490000
0*
#495000
0(
1'
b110010 ,
1*
#500000
0*
1)
#505000
0'
0$
0#
b0 ,
1*
