4.5/LED45_blink.v

module DebouncedButton (
    input wire CLK,
    input wire SW2,
    output wire btn_pressed
);
    reg [3:0] debounce_count = 4'b1000;  // Contador para el debounce
    reg pressed = 1'b0;
    reg btn_last = 1'b0;  // Almacena el estado anterior del botón

    assign btn_pressed = pressed;  // Señal de botón pulsado

    always @(posedge CLK) begin
        if(SW2)
            if (debounce_count > 0)
                debounce_count <= debounce_count - 1;
            else if (debounce_count == 0) begin // Han pasado 10 ms desde el flanco de subida del botón
                if(btn_last == 1'b0) begin
                    pressed <= 1'b1;
                    btn_last <= 1'b1;
                end else if(btn_last == 1'b1)
                    pressed <= 1'b0;
            end
        else begin
            pressed <= 1'b0;
            debounce_count <= 4'b1000;
            btn_last <= 1'b0;
        end       
    end
endmodule



module LED_blink (
    input wire CLK,
    input wire SW2,
    input wire SW1,  
    output wire LED0, LED1, LED2, LED3, LED4, LED5, LED6, LED7
);
    wire btn_pressed1;
    wire btn_pressed2;

    reg [27:0] data = 0;
    reg add_mode = 1'b1;  // Modo de suma/resta

    // Instancia del módulo DebouncedButton
    DebouncedButton btn_debouncer2 (
        .CLK(CLK),
        .SW2(SW2),
        .btn_pressed(btn_pressed2)
    );

    DebouncedButton btn_debouncer1 (
        .CLK(CLK),
        .SW2(SW1),
        .btn_pressed(btn_pressed1)
    );

    // Asignación: bits 20 a 27 de data se asignan a las salidas LED
    assign LED0 = data[0];
    assign LED1 = data[1];
    assign LED2 = data[2];
    assign LED3 = data[3];
    assign LED4 = data[4];
    assign LED5 = data[5];
    assign LED6 = data[6];
    assign LED7 = data[7];

    // Contador: incrementa o decrementa según el modo
    always @(posedge CLK) begin
        if (btn_pressed1) begin  // Si el botón 1 se ha pulsado, invertir el modo
            if( add_mode == 1'b1)
                add_mode <= 1'b0;
            else if(add_mode == 1'b0)
                add_mode <= 1'b1;
        end else if (btn_pressed2) begin  // Si el botón 2 se ha pulsado, reiniciar el contador
            data <= 0;
        end else if (add_mode == 1'b1)  // Si está en modo suma
            data <= data + 1;
        else if (add_mode == 1'b0)  // Si está en modo resta
            data <= data - 1;
    end
endmodule

4.5/LED45_blink_tb.v
`timescale 1ns/100ps

module testbench ();
    reg clk = 0;
    reg button2 = 0;
    reg button1 = 0;
    wire led0, led1, led2, led3, led4, led5, led6, led7;

    // Generamos reloj
    // Periodo = 5 * timescale = 5 * 1ns
    localparam CLOCK_PERIOD = 5;

    // Inicialmente está a 0
    initial clk = 1'b0;

    // Cambio valor de clk cada 5ns
    always #CLOCK_PERIOD clk = ~clk;

    // INICIALIZO BOTONES
    initial begin
        button2 = 0;
        button1 = 0;
        #500;    // 5ms
        button2 = 1;
        #500;    // 5ms
        button2 = 0;
        #100;
        button1 = 1;
        #500;
        button1 = 0;

    end

    reg errores = 0;

    // Instancia del módulo LED_blink
    LED_blink DUT (
        .CLK(clk),
        .SW2(button2),
        .SW1(button1),
        .LED0(led0),
        .LED1(led1),
        .LED2(led2),
        .LED3(led3),
        .LED4(led4),
        .LED5(led5),
        .LED6(led6),
        .LED7(led7)
    );

    // Verificar el comportamiento esperado
    initial begin
        $dumpfile(`DUMPSTR("LED45_blink_tb.vcd"));
        $dumpvars(0, testbench);
        #1;
        if (!(led0 === 0 && led1 === 0 && led2 === 0 && led3 === 0 && led4 === 0 && led5 === 0 && led6 === 0 && led7 === 0))
        begin
            $display("Error: LEDs no están en 0 al inicio");
            errores = errores + 1;
        end
        // Comprobación después de 10 ms del flanco del boton
        #600;
        // Comprobar si los LEDs son los esperados despues del reset
        if (!(led0 === 0 && led1 === 0 && led2 === 0 && led3 === 0 && led4 === 0 && led5 === 0 && led6 === 0 && led7 === 0))
        begin
            $display("Error: Configuración de LEDs incorrecta después del reset");
            errores = errores + 1;
        end
        #800; // esperar a un total de 1400
        if (!(led0 === 1 && led1 === 1 && led2 === 1 && led3 === 0 && led4 === 0 && led5 === 1 && led6 === 0 && led7 === 0))
        begin
            $display("Error: Configuración de LEDs incorrecta después del cambio de modo");
            errores = errores + 1;
        end

        if (errores === 0)
            $display("\nTestbench completado sin errores\n");
        else
            $display("\nTestbench completado con %d errores\n", errores);
        #500;

        $finish;
    end
endmodule

4.5/LED44_blink_tb.vcd
$date
	Thu Dec 28 21:33:30 2023
$end
$version
	Icarus Verilog
$end
$timescale
	1ps
$end
$scope module testbench $end
$var wire 1 ! led7 $end
$var wire 1 " led6 $end
$var wire 1 # led5 $end
$var wire 1 $ led4 $end
$var wire 1 % led3 $end
$var wire 1 & led2 $end
$var wire 1 ' led1 $end
$var wire 1 ( led0 $end
$var reg 1 ) button1 $end
$var reg 1 * button2 $end
$var reg 1 + clk $end
$var reg 1 , errores $end
$scope module DUT $end
$var wire 1 + CLK $end
$var wire 1 ) SW1 $end
$var wire 1 * SW2 $end
$var wire 1 - btn_pressed2 $end
$var wire 1 . btn_pressed1 $end
$var wire 1 ! LED7 $end
$var wire 1 " LED6 $end
$var wire 1 # LED5 $end
$var wire 1 $ LED4 $end
$var wire 1 % LED3 $end
$var wire 1 & LED2 $end
$var wire 1 ' LED1 $end
$var wire 1 ( LED0 $end
$var reg 1 / add_mode $end
$var reg 28 0 data [27:0] $end
$scope module btn_debouncer1 $end
$var wire 1 + CLK $end
$var wire 1 ) SW2 $end
$var wire 1 . btn_pressed $end
$var reg 1 1 btn_last $end
$var reg 4 2 debounce_count [3:0] $end
$var reg 1 3 pressed $end
$upscope $end
$scope module btn_debouncer2 $end
$var wire 1 + CLK $end
$var wire 1 * SW2 $end
$var wire 1 - btn_pressed $end
$var reg 1 4 btn_last $end
$var reg 4 5 debounce_count [3:0] $end
$var reg 1 6 pressed $end
$upscope $end
$upscope $end
$upscope $end
$enddefinitions $end
#0
$dumpvars
06
b1111 5
04
03
b1111 2
01
b0 0
1/
0.
0-
0,
0+
0*
0)
0(
0'
0&
0%
0$
0#
0"
0!
$end
#5000
1(
b1 0
1+
#10000
0+
#15000
0(
1'
b10 0
1+
#20000
0+
#25000
1(
b11 0
1+
#30000
0+
#35000
0(
0'
1&
b100 0
1+
#40000
0+
#45000
1(
b101 0
1+
#50000
0+
#55000
0(
1'
b110 0
1+
#60000
0+
#65000
1(
b111 0
1+
#70000
0+
#75000
0(
0'
0&
1%
b1000 0
1+
#80000
0+
#85000
1(
b1001 0
1+
#90000
0+
#95000
0(
1'
b1010 0
1+
#100000
0+
#105000
1(
b1011 0
1+
#110000
0+
#115000
0(
0'
1&
b1100 0
1+
#120000
0+
#125000
1(
b1101 0
1+
#130000
0+
#135000
0(
1'
b1110 0
1+
#140000
0+
#145000
1(
b1111 0
1+
#150000
0+
#155000
0(
0'
0&
0%
1$
b10000 0
1+
#160000
0+
#165000
1(
b10001 0
1+
#170000
0+
#175000
0(
1'
b10010 0
1+
#180000
0+
#185000
1(
b10011 0
1+
#190000
0+
#195000
0(
0'
1&
b10100 0
1+
#200000
0+
#205000
1(
b10101 0
1+
#210000
0+
#215000
0(
1'
b10110 0
1+
#220000
0+
#225000
1(
b10111 0
1+
#230000
0+
#235000
0(
0'
0&
1%
b11000 0
1+
#240000
0+
#245000
1(
b11001 0
1+
#250000
0+
#255000
0(
1'
b11010 0
1+
#260000
0+
#265000
1(
b11011 0
1+
#270000
0+
#275000
0(
0'
1&
b11100 0
1+
#280000
0+
#285000
1(
b11101 0
1+
#290000
0+
#295000
0(
1'
b11110 0
1+
#300000
0+
#305000
1(
b11111 0
1+
#310000
0+
#315000
0(
0'
0&
0%
0$
1#
b100000 0
1+
#320000
0+
#325000
1(
b100001 0
1+
#330000
0+
#335000
0(
1'
b100010 0
1+
#340000
0+
#345000
1(
b100011 0
1+
#350000
0+
#355000
0(
0'
1&
b100100 0
1+
#360000
0+
#365000
1(
b100101 0
1+
#370000
0+
#375000
0(
1'
b100110 0
1+
#380000
0+
#385000
1(
b100111 0
1+
#390000
0+
#395000
0(
0'
0&
1%
b101000 0
1+
#400000
0+
#405000
1(
b101001 0
1+
#410000
0+
#415000
0(
1'
b101010 0
1+
#420000
0+
#425000
1(
b101011 0
1+
#430000
0+
#435000
0(
0'
1&
b101100 0
1+
#440000
0+
#445000
1(
b101101 0
1+
#450000
0+
#455000
0(
1'
b101110 0
1+
#460000
0+
#465000
1(
b101111 0
1+
#470000
0+
#475000
0(
0'
0&
0%
1$
b110000 0
1+
#480000
0+
#485000
1(
b110001 0
1+
#490000
0+
#495000
0(
1'
b110010 0
1+
#500000
0+
1*
#505000
1(
b1110 5
b110011 0
1+
#510000
0+
#515000
0(
0'
1&
b1101 5
b110100 0
1+
#520000
0+
#525000
1(
b1100 5
b110101 0
1+
#530000
0+
#535000
0(
1'
b1011 5
b110110 0
1+
#540000
0+
#545000
1(
b1010 5
b110111 0
1+
#550000
0+
#555000
0(
0'
0&
1%
b1001 5
b111000 0
1+
#560000
0+
#565000
1(
b1000 5
b111001 0
1+
#570000
0+
#575000
0(
1'
b111 5
b111010 0
1+
#580000
0+
#585000
1(
b110 5
b111011 0
1+
#590000
0+
#595000
0(
0'
1&
b101 5
b111100 0
1+
#600000
0+
#605000
1(
b100 5
b111101 0
1+
#610000
0+
#615000
0(
1'
b11 5
b111110 0
1+
#620000
0+
#625000
1(
b10 5
b111111 0
1+
#630000
0+
#635000
0(
0'
0&
0%
0$
0#
1"
b1 5
b1000000 0
1+
#640000
0+
#645000
1(
b0 5
b1000001 0
1+
#650000
0+
#655000
1(
1'
14
1-
16
b1000011 0
1+
#660000
0+
#661000
1,
#665000
1&
0(
0'
0-
06
b1000100 0
1+
#670000
0+
#675000
1(
b1000101 0
1+
#680000
0+
#685000
0(
1'
b1000110 0
1+
#690000
0+
#695000
1(
b1000111 0
1+
#700000
0+
#705000
0(
0'
0&
1%
b1001000 0
1+
#710000
0+
#715000
1(
b1001001 0
1+
#720000
0+
#725000
0(
1'
b1001010 0
1+
#730000
0+
#735000
1(
b1001011 0
1+
#740000
0+
#745000
0(
0'
1&
b1001100 0
1+
#750000
0+
#755000
1(
b1001101 0
1+
#760000
0+
#765000
0(
1'
b1001110 0
1+
#770000
0+
#775000
1(
b1001111 0
1+
#780000
0+
#785000
0(
0'
0&
0%
1$
b1010000 0
1+
#790000
0+
#795000
1(
b1010001 0
1+
#800000
0+
#805000
0(
1'
b1010010 0
1+
#810000
0+
#815000
1(
b1010011 0
1+
#820000
0+
#825000
0(
0'
1&
b1010100 0
1+
#830000
0+
#835000
1(
b1010101 0
1+
#840000
0+
#845000
0(
1'
b1010110 0
1+
#850000
0+
#855000
1(
b1010111 0
1+
#860000
0+
#865000
0(
0'
0&
1%
b1011000 0
1+
#870000
0+
#875000
1(
b1011001 0
1+
#880000
0+
#885000
0(
1'
b1011010 0
1+
#890000
0+
#895000
1(
b1011011 0
1+
#900000
0+
#905000
0(
0'
1&
b1011100 0
1+
#910000
0+
#915000
1(
b1011101 0
1+
#920000
0+
#925000
0(
1'
b1011110 0
1+
#930000
0+
#935000
1(
b1011111 0
1+
#940000
0+
#945000
0(
0'
0&
0%
0$
1#
b1100000 0
1+
#950000
0+
#955000
1(
b1100001 0
1+
#960000
0+
#965000
0(
1'
b1100010 0
1+
#970000
0+
#975000
1(
b1100011 0
1+
#980000
0+
#985000
0(
0'
1&
b1100100 0
1+
#990000
0+
#995000
1(
b1100101 0
1+
#1000000
0+
0*
#1005000
0(
1'
b1100110 0
1+
#1010000
0+
#1015000
1(
b1100111 0
1+
#1020000
0+
#1025000
0(
0'
0&
1%
b1101000 0
1+
#1030000
0+
#1035000
1(
b1101001 0
1+
#1040000
0+
#1045000
0(
1'
b1101010 0
1+
#1050000
0+
#1055000
1(
b1101011 0
1+
#1060000
0+
#1065000
0(
0'
1&
b1101100 0
1+
#1070000
0+
#1075000
1(
b1101101 0
1+
#1080000
0+
#1085000
0(
1'
b1101110 0
1+
#1090000
0+
#1095000
1(
b1101111 0
1+
#1100000
0+
#1105000
0(
0'
0&
0%
1$
b1110000 0
1+
#1110000
0+
#1115000
1(
b1110001 0
1+
#1120000
0+
#1125000
0(
1'
b1110010 0
1+
#1130000
0+
#1135000
1(
b1110011 0
1+
#1140000
0+
#1145000
0(
0'
1&
b1110100 0
1+
#1150000
0+
#1155000
1(
b1110101 0
1+
