4.8/LED48_blink.v
module LED_blink (
    input wire CLK,
    output wire LED0, LED1, LED2, LED3, LED4, LED5, LED6, LED7
);

    reg [27:0] data = 0;
    reg add_mode = 1'b1; // modo suma/resta
    reg [2:0] prev_led = 3'b0; // Variable para rastrear el LED encendido anteriormente

    // Asignación: bits 20 a 27 de data se asignan a las salidas LED
    assign LED0 = data[0];
    assign LED1 = data[1];
    assign LED2 = data[2];
    assign LED3 = data[3];
    assign LED4 = data[4];
    assign LED5 = data[5];
    assign LED6 = data[6];
    assign LED7 = data[7];

    always @(posedge CLK) begin
        if (add_mode == 1'b1) begin
            data <= data << 1; // Desplazar el patrón de barrido hacia la izquierda
            case (prev_led)
                3'b000: data[0] <= 1'b1; // Encender el LED 0
                3'b001: data[1] <= 1'b1; // Encender el LED 1
                3'b010: data[2] <= 1'b1; // Encender el LED 2
                3'b011: data[3] <= 1'b1; // Encender el LED 3
                3'b100: data[4] <= 1'b1; // Encender el LED 4
                3'b101: data[5] <= 1'b1; // Encender el LED 5
                3'b110: data[6] <= 1'b1; // Encender el LED 6
                3'b111: data[7] <= 1'b1; // Encender el LED 7
            endcase
            if (prev_led == 3'b111) // si ha llegado al final, cambia al modo de resta
                add_mode <= 1'b0;
            else
                prev_led <= prev_led + 1; // Cambiar al siguiente LED

        end else if (add_mode == 1'b0) begin
            data <= data >> 1; // Desplazar el patrón de barrido hacia la derecha
            case (prev_led)
                3'b000: data[0] <= 1'b1; // Encender el LED 0
                3'b001: data[1] <= 1'b1; // Encender el LED 1
                3'b010: data[2] <= 1'b1; // Encender el LED 2
                3'b011: data[3] <= 1'b1; // Encender el LED 3
                3'b100: data[4] <= 1'b1; // Encender el LED 4
                3'b101: data[5] <= 1'b1; // Encender el LED 5
                3'b110: data[6] <= 1'b1; // Encender el LED 6
                3'b111: data[7] <= 1'b1; // Encender el LED 7
            endcase
            if (prev_led == 3'b000) // si ha llegado al inicio, cambia al modo de suma
                add_mode <= 1'b1;
            else
                prev_led <= prev_led - 1; // Cambiar al anterior LED
        
        end
    end
endmodule

4.8/LED48_blink_tb.v
`timescale 1ns/100ps

module testbench ();
    reg clk = 0;
    wire led0, led1, led2, led3, led4, led5, led6, led7;

    // Generamos reloj
    // Periodo = 5 * timescale = 5 * 1ns
    localparam CLOCK_PERIOD = 5;

    // Inicialmente está a 0
    initial clk = 1'b0;

    // Cambio valor de clk cada 5ns
    always #CLOCK_PERIOD clk = ~clk;


    // Instancia del módulo LED_blink
    LED_blink DUT (
        .CLK(clk),
        .LED0(led0),
        .LED1(led1),
        .LED2(led2),
        .LED3(led3),
        .LED4(led4),
        .LED5(led5),
        .LED6(led6),
        .LED7(led7)
    );

    // Verificar el comportamiento esperado
    initial begin
        $dumpfile(`DUMPSTR("LED48_blink_tb.vcd"));
        $dumpvars(0, testbench);
        #5000;

        $finish;
    end
endmodule

4.8/LED48_blink_tb.vcd
$date
	Fri Dec 29 19:50:23 2023
$end
$version
	Icarus Verilog
$end
$timescale
	1ps
$end
$scope module testbench $end
$var wire 1 ! led7 $end
$var wire 1 " led6 $end
$var wire 1 # led5 $end
$var wire 1 $ led4 $end
$var wire 1 % led3 $end
$var wire 1 & led2 $end
$var wire 1 ' led1 $end
$var wire 1 ( led0 $end
$var reg 1 ) clk $end
$scope module DUT $end
$var wire 1 ) CLK $end
$var wire 1 ! LED7 $end
$var wire 1 " LED6 $end
$var wire 1 # LED5 $end
$var wire 1 $ LED4 $end
$var wire 1 % LED3 $end
$var wire 1 & LED2 $end
$var wire 1 ' LED1 $end
$var wire 1 ( LED0 $end
$var reg 1 * add_mode $end
$var reg 28 + data [27:0] $end
$var reg 3 , prev_led [2:0] $end
$upscope $end
$upscope $end
$enddefinitions $end
#0
$dumpvars
b0 ,
b0 +
1*
0)
0(
0'
0&
0%
0$
0#
0"
0!
$end
#5000
1(
b1 ,
b1 +
1)
#10000
0)
#15000
0(
1'
b10 ,
b10 +
1)
#20000
0)
#25000
0'
1&
b11 ,
b100 +
1)
#30000
0)
#35000
0&
1%
b100 ,
b1000 +
1)
#40000
0)
#45000
0%
1$
b101 ,
b10000 +
1)
#50000
0)
#55000
0$
1#
b110 ,
b100000 +
1)
#60000
0)
#65000
0#
1"
b111 ,
b1000000 +
1)
#70000
0)
#75000
0"
1!
0*
b10000000 +
1)
#80000
0)
#85000
1"
b110 ,
b11000000 +
1)
#90000
0)
#95000
1#
0!
b101 ,
b1100000 +
1)
#100000
0)
#105000
1$
0"
b100 ,
b110000 +
1)
#110000
0)
#115000
1%
0#
b11 ,
b11000 +
1)
#120000
0)
#125000
1&
0$
b10 ,
b1100 +
1)
#130000
0)
#135000
1'
0%
b1 ,
b110 +
1)
#140000
0)
#145000
1(
0&
b0 ,
b11 +
1)
#150000
0)
#155000
0'
1*
b1 +
1)
#160000
0)
#165000
1'
b1 ,
b11 +
1)
#170000
0)
#175000
0(
1&
b10 ,
b110 +
1)
#180000
0)
#185000
0'
1%
b11 ,
b1100 +
1)
#190000
0)
#195000
0&
1$
b100 ,
b11000 +
1)
#200000
0)
#205000
0%
1#
b101 ,
b110000 +
1)
#210000
0)
#215000
0$
1"
b110 ,
b1100000 +
1)
#220000
0)
#225000
0#
1!
b111 ,
b11000000 +
1)
#230000
0)
#235000
0"
0*
b110000000 +
1)
#240000
0)
#245000
1"
b110 ,
b11000000 +
1)
#250000
0)
#255000
1#
0!
b101 ,
b1100000 +
1)
#260000
0)
#265000
1$
0"
b100 ,
b110000 +
1)
#270000
0)
#275000
1%
0#
b11 ,
b11000 +
1)
#280000
0)
#285000
1&
0$
b10 ,
b1100 +
1)
#290000
0)
#295000
1'
0%
b1 ,
b110 +
1)
#300000
0)
#305000
1(
0&
b0 ,
b11 +
1)
#310000
0)
#315000
0'
1*
b1 +
1)
#320000
0)
#325000
1'
b1 ,
b11 +
1)
#330000
0)
#335000
0(
1&
b10 ,
b110 +
1)
#340000
0)
#345000
0'
1%
b11 ,
b1100 +
1)
#350000
0)
#355000
0&
1$
b100 ,
b11000 +
1)
#360000
0)
#365000
0%
1#
b101 ,
b110000 +
1)
#370000
0)
#375000
0$
1"
b110 ,
b1100000 +
1)
#380000
0)
#385000
0#
1!
b111 ,
b11000000 +
1)
#390000
0)
#395000
0"
0*
b110000000 +
1)
#400000
0)
#405000
1"
b110 ,
b11000000 +
1)
#410000
0)
#415000
1#
0!
b101 ,
b1100000 +
1)
#420000
0)
#425000
1$
0"
b100 ,
b110000 +
1)
#430000
0)
#435000
1%
0#
b11 ,
b11000 +
1)
#440000
0)
#445000
1&
0$
b10 ,
b1100 +
1)
#450000
0)
#455000
1'
0%
b1 ,
b110 +
1)
#460000
0)
#465000
1(
0&
b0 ,
b11 +
1)
#470000
0)
#475000
0'
1*
b1 +
1)
#480000
0)
#485000
1'
b1 ,
b11 +
1)
#490000
0)
#495000
0(
1&
b10 ,
b110 +
1)
#500000
0)
#505000
0'
1%
b11 ,
b1100 +
1)
#510000
0)
#515000
0&
1$
b100 ,
b11000 +
1)
#520000
0)
#525000
0%
1#
b101 ,
b110000 +
1)
#530000
0)
#535000
0$
1"
b110 ,
b1100000 +
1)
#540000
0)
#545000
0#
1!
b111 ,
b11000000 +
1)
#550000
0)
#555000
0"
0*
b110000000 +
1)
#560000
0)
#565000
1"
b110 ,
b11000000 +
1)
#570000
0)
#575000
1#
0!
b101 ,
b1100000 +
1)
#580000
0)
#585000
1$
0"
b100 ,
b110000 +
1)
#590000
0)
#595000
1%
0#
b11 ,
b11000 +
1)
#600000
0)
#605000
1&
0$
b10 ,
b1100 +
1)
#610000
0)
#615000
1'
0%
b1 ,
b110 +
1)
#620000
0)
#625000
1(
0&
b0 ,
b11 +
1)
#630000
0)
#635000
0'
1*
b1 +
1)
#640000
0)
#645000
1'
b1 ,
b11 +
1)
#650000
0)
#655000
0(
1&
b10 ,
b110 +
1)
#660000
0)
#665000
0'
1%
b11 ,
b1100 +
1)
#670000
0)
#675000
0&
1$
b100 ,
b11000 +
1)
#680000
0)
#685000
0%
1#
b101 ,
b110000 +
1)
#690000
0)
#695000
0$
1"
b110 ,
b1100000 +
1)
#700000
0)
#705000
0#
1!
b111 ,
b11000000 +
1)
#710000
0)
#715000
0"
0*
b110000000 +
1)
#720000
0)
#725000
1"
b110 ,
b11000000 +
1)
#730000
0)
#735000
1#
0!
b101 ,
b1100000 +
1)
#740000
0)
#745000
1$
0"
b100 ,
b110000 +
1)
#750000
0)
#755000
1%
0#
b11 ,
b11000 +
1)
#760000
0)
#765000
1&
0$
b10 ,
b1100 +
1)
#770000
0)
#775000
1'
0%
b1 ,
b110 +
1)
#780000
0)
#785000
1(
0&
b0 ,
b11 +
1)
#790000
0)
#795000
0'
1*
b1 +
1)
#800000
0)
#805000
1'
b1 ,
b11 +
1)
#810000
0)
#815000
0(
1&
b10 ,
b110 +
1)
#820000
0)
#825000
0'
1%
b11 ,
b1100 +
1)
#830000
0)
#835000
0&
1$
b100 ,
b11000 +
1)
#840000
0)
#845000
0%
1#
b101 ,
b110000 +
1)
#850000
0)
#855000
0$
1"
b110 ,
b1100000 +
1)
#860000
0)
#865000
0#
1!
b111 ,
b11000000 +
1)
#870000
0)
#875000
0"
0*
b110000000 +
1)
#880000
0)
#885000
1"
b110 ,
b11000000 +
1)
#890000
0)
#895000
1#
0!
b101 ,
b1100000 +
1)
#900000
0)
#905000
1$
0"
b100 ,
b110000 +
1)
#910000
0)
#915000
1%
0#
b11 ,
b11000 +
1)
#920000
0)
#925000
1&
0$
b10 ,
b1100 +
1)
#930000
0)
#935000
1'
0%
b1 ,
b110 +
1)
#940000
0)
#945000
1(
0&
b0 ,
b11 +
1)
#950000
0)
#955000
0'
1*
b1 +
1)
#960000
0)
#965000
1'
b1 ,
b11 +
1)
#970000
0)
#975000
0(
1&
b10 ,
b110 +
1)
#980000
0)
#985000
0'
1%
b11 ,
b1100 +
1)
#990000
0)
#995000
0&
1$
b100 ,
b11000 +
1)
#1000000
0)
#1005000
0%
1#
b101 ,
b110000 +
1)
#1010000
0)
#1015000
0$
1"
b110 ,
b1100000 +
1)
#1020000
0)
#1025000
0#
1!
b111 ,
b11000000 +
1)
#1030000
0)
#1035000
0"
0*
b110000000 +
1)
#1040000
0)
#1045000
1"
b110 ,
b11000000 +
1)
#1050000
0)
#1055000
1#
0!
b101 ,
b1100000 +
1)
#1060000
0)
#1065000
1$
0"
b100 ,
b110000 +
1)
#1070000
0)
#1075000
1%
0#
b11 ,
b11000 +
1)
#1080000
0)
#1085000
1&
0$
b10 ,
b1100 +
1)
#1090000
0)
#1095000
1'
0%
b1 ,
b110 +
1)
#1100000
0)
#1105000
1(
0&
b0 ,
b11 +
1)
#1110000
0)
#1115000
0'
1*
b1 +
1)
#1120000
0)
#1125000
1'
b1 ,
b11 +
1)
#1130000
0)
#1135000
0(
1&
b10 ,
b110 +
1)
#1140000
0)
#1145000
0'
1%
b11 ,
b1100 +
1)
#1150000
0)
#1155000
0&
1$
b100 ,
b11000 +
1)
#1160000
0)
#1165000
0%
1#
b101 ,
b110000 +
1)
#1170000
0)
#1175000
0$
1"
b110 ,
b1100000 +
1)
#1180000
0)
#1185000
0#
1!
b111 ,
b11000000 +
1)
#1190000
0)
#1195000
0"
0*
b110000000 +
1)
#1200000
0)
#1205000
1"
b110 ,
b11000000 +
1)
#1210000
0)
#1215000
1#
0!
b101 ,
b1100000 +
1)
#1220000
0)
#1225000
1$
0"
b100 ,
b110000 +
1)
#1230000
0)
#1235000
1%
0#
b11 ,
b11000 +
1)
#1240000
0)
#1245000
1&
0$
b10 ,
b1100 +
1)
#1250000
0)
#1255000
1'
0%
b1 ,
b110 +
1)
#1260000
0)
#1265000
1(
0&
b0 ,
b11 +
1)
#1270000
0)
#1275000
0'
1*
b1 +
1)
#1280000
0)
#1285000
1'
b1 ,
b11 +
1)
#1290000
0)
#1295000
0(
1&
b10 ,
b110 +
1)
#1300000
0)
#1305000
0'
1%
b11 ,
b1100 +
1)
#1310000
0)
#1315000
0&
1$
b100 ,
b11000 +
1)
#1320000
0)
#1325000
0%
1#
b101 ,
b110000 +
1)
#1330000
0)
#1335000
0$
1"
b110 ,
b1100000 +
1)
#1340000
0)
#1345000
0#
1!
b111 ,
b11000000 +
1)
#1350000
0)
#1355000
0"
0*
b110000000 +
1)
#1360000
0)
#1365000
1"
b110 ,
b11000000 +
1)
#1370000
0)
#1375000
1#
0!
b101 ,
b1100000 +
1)
#1380000
0)
#1385000
1$
0"
b100 ,
b110000 +
1)
#1390000
0)
#1395000
1%
0#
b11 ,
b11000 +
1)
#1400000
0)
#1405000
1&
0$
b10 ,
b1100 +
1)
#1410000
0)
#1415000
1'
0%
b1 ,
b110 +
1)
#1420000
0)
#1425000
1(
0&
b0 ,
b11 +
1)
#1430000
0)
#1435000
0'
1*
b1 +
1)
#1440000
0)
#1445000
1'
b1 ,
b11 +
1)
#1450000
0)
#1455000
0(
1&
b10 ,
b110 +
1)
#1460000
0)
#1465000
0'
1%
b11 ,
b1100 +
1)
#1470000
0)
#1475000
0&
1$
b100 ,
b11000 +
1)
#1480000
0)
#1485000
0%
1#
b101 ,
b110000 +
1)
#1490000
0)
#1495000
0$
1"
b110 ,
b1100000 +
1)
#1500000
0)
#1505000
0#
1!
b111 ,
b11000000 +
1)
#1510000
0)
#1515000
0"
0*
b110000000 +
1)
#1520000
0)
#1525000
1"
b110 ,
b11000000 +
1)
#1530000
0)
#1535000
1#
0!
b101 ,
b1100000 +
1)
#1540000
0)
#1545000
1$
0"
b100 ,
b110000 +
1)
#1550000
0)
#1555000
1%
0#
b11 ,
b11000 +
1)
#1560000
0)
#1565000
1&
0$
b10 ,
b1100 +
1)
#1570000
0)
#1575000
1'
0%
b1 ,
b110 +
1)
#1580000
0)
#1585000
1(
0&
b0 ,
b11 +
1)
#1590000
0)
#1595000
0'
1*
b1 +
1)
#1600000
0)
#1605000
1'
b1 ,
b11 +
1)
#1610000
0)
#1615000
0(
1&
b10 ,
b110 +
1)
#1620000
0)
#1625000
0'
1%
b11 ,
b1100 +
1)
#1630000
0)
#1635000
0&
1$
b100 ,
b11000 +
1)
#1640000
0)
#1645000
0%
1#
b101 ,
b110000 +
1)
#1650000
0)
#1655000
0$
1"
b110 ,
b1100000 +
1)
#1660000
0)
#1665000
0#
1!
b111 ,
b11000000 +
1)
#1670000
0)
#1675000
0"
0*
b110000000 +
1)
#1680000
0)
#1685000
1"
b110 ,
b11000000 +
1)
#1690000
0)
#1695000
1#
0!
b101 ,
b1100000 +
1)
#1700000
0)
#1705000
1$
0"
b100 ,
b110000 +
1)
#1710000
0)
#1715000
1%
0#
b11 ,
b11000 +
1)
#1720000
0)
#1725000
1&
0$
b10 ,
b1100 +
1)
#1730000
0)
#1735000
1'
0%
b1 ,
b110 +
1)
#1740000
0)
#1745000
1(
0&
b0 ,
b11 +
1)
#1750000
0)
#1755000
0'
1*
b1 +
1)
#1760000
0)
#1765000
1'
b1 ,
b11 +
1)
#1770000
0)
#1775000
0(
1&
b10 ,
b110 +
1)
#1780000
0)
#1785000
0'
1%
b11 ,
b1100 +
1)
#1790000
0)
#1795000
0&
1$
b100 ,
b11000 +
1)
#1800000
0)
#1805000
0%
1#
b101 ,
b110000 +
1)
#1810000
0)
#1815000
0$
1"
b110 ,
b1100000 +
1)
#1820000
0)
#1825000
0#
1!
b111 ,
b11000000 +
1)
#1830000
0)
#1835000
0"
0*
b110000000 +
1)
#1840000
0)
#1845000
1"
b110 ,
b11000000 +
1)
#1850000
0)
#1855000
1#
0!
b101 ,
b1100000 +
1)
#1860000
0)
#1865000
1$
0"
b100 ,
b110000 +
1)
#1870000
0)
#1875000
1%
0#
b11 ,
b11000 +
1)
#1880000
0)
#1885000
1&
0$
b10 ,
b1100 +
1)
#1890000
0)
#1895000
1'
0%
b1 ,
b110 +
1)
#1900000
0)
#1905000
1(
0&
b0 ,
b11 +
1)
#1910000
0)
#1915000
0'
1*
b1 +
1)
#1920000
0)
#1925000
1'
b1 ,
b11 +
1)
#1930000
0)
#1935000
0(
1&
b10 ,
b110 +
1)
#1940000
0)
#1945000
0'
1%
b11 ,
b1100 +
1)
#1950000
0)
#1955000
0&
1$
b100 ,
b11000 +
1)
#1960000
0)
#1965000
0%
1#
b101 ,
b110000 +
1)
#1970000
0)
#1975000
0$
1"
b110 ,
b1100000 +
1)
#1980000
0)
#1985000
0#
1!
b111 ,
b11000000 +
1)
#1990000
0)
#1995000
0"
0*
b110000000 +
1)
#2000000
0)
#2005000
1"
b110 ,
b11000000 +
1)
#2010000
0)
#2015000
1#
0!
b101 ,
b1100000 +
1)
#2020000
0)
#2025000
1$
0"
b100 ,
b110000 +
1)
#2030000
0)
#2035000
1%
0#
b11 ,
b11000 +
1)
#2040000
0)
#2045000
1&
0$
b10 ,
b1100 +
1)
#2050000
0)
#2055000
1'
0%
b1 ,
b110 +
1)
#2060000
0)
#2065000
1(
0&
b0 ,
b11 +
1)
#2070000
0)
#2075000
0'
1*
b1 +
1)
#2080000
0)
#2085000
1'
b1 ,
b11 +
1)
#2090000
0)
#2095000
0(
1&
b10 ,
b110 +
1)
#2100000
0)
#2105000
0'
1%
b11 ,
b1100 +
1)
#2110000
0)
#2115000
0&
1$
b100 ,
b11000 +
1)
#2120000
0)
#2125000
0%
1#
b101 ,
b110000 +
1)
#2130000
0)
#2135000
0$
1"
b110 ,
b1100000 +
1)
#2140000
0)
#2145000
0#
1!
b111 ,
b11000000 +
1)
#2150000
0)
#2155000
0"
0*
b110000000 +
1)
#2160000
0)
#2165000
1"
b110 ,
b11000000 +
1)
#2170000
0)
#2175000
1#
0!
b101 ,
b1100000 +
1)
#2180000
0)
#2185000
1$
0"
b100 ,
b110000 +
1)
#2190000
0)
#2195000
1%
0#
b11 ,
b11000 +
1)
#2200000
0)
#2205000
1&
0$
b10 ,
b1100 +
1)
#2210000
0)
#2215000
1'
0%
b1 ,
b110 +
1)
#2220000
0)
#2225000
1(
0&
b0 ,
b11 +
1)
#2230000
0)
#2235000
0'
1*
b1 +
1)
#2240000
0)
#2245000
1'
b1 ,
b11 +
1)
#2250000
0)
#2255000
0(
1&
b10 ,
b110 +
1)
#2260000
0)
#2265000
0'
1%
b11 ,
b1100 +
1)
#2270000
0)
#2275000
0&
1$
b100 ,
b11000 +
1)
#2280000
0)
#2285000
0%
1#
b101 ,
b110000 +
1)
#2290000
0)
#2295000
0$
1"
b110 ,
b1100000 +
1)
#2300000
0)
#2305000
0#
1!
b111 ,
b11000000 +
1)
#2310000
0)
#2315000
0"
0*
b110000000 +
1)
#2320000
0)
#2325000
1"
b110 ,
b11000000 +
1)
#2330000
0)
#2335000
1#
0!
b101 ,
b1100000 +
1)
#2340000
0)
#2345000
1$
0"
b100 ,
b110000 +
1)
#2350000
0)
#2355000
1%
0#
b11 ,
b11000 +
1)
#2360000
0)
#2365000
1&
0$
b10 ,
b1100 +
1)
#2370000
0)
#2375000
1'
0%
b1 ,
b110 +
1)
#2380000
0)
#2385000
1(
0&
b0 ,
b11 +
1)
#2390000
0)
#2395000
0'
1*
b1 +
1)
#2400000
0)
#2405000
1'
b1 ,
b11 +
1)
#2410000
0)
#2415000
0(
1&
b10 ,
b110 +
1)
#2420000
0)
#2425000
0'
1%
b11 ,
b1100 +
1)
#2430000
0)
#2435000
0&
1$
b100 ,
b11000 +
1)
#2440000
0)
#2445000
0%
1#
b101 ,
b110000 +
1)
#2450000
0)
#2455000
0$
1"
b110 ,
b1100000 +
1)
#2460000
0)
#2465000
0#
1!
b111 ,
b11000000 +
1)
#2470000
0)
#2475000
0"
0*
b110000000 +
1)
#2480000
0)
#2485000
1"
b110 ,
b11000000 +
1)
#2490000
0)
#2495000
1#
0!
b101 ,
b1100000 +
1)
#2500000
0)
#2505000
1$
0"
b100 ,
b110000 +
1)
#2510000
0)
#2515000
1%
0#
b11 ,
b11000 +
1)
#2520000
0)
#2525000
1&
0$
b10 ,
b1100 +
1)
#2530000
0)
#2535000
1'
0%
b1 ,
b110 +
1)
#2540000
0)
#2545000
1(
0&
b0 ,
b11 +
1)
#2550000
0)
#2555000
0'
1*
b1 +
1)
#2560000
0)
#2565000
1'
b1 ,
b11 +
1)
#2570000
0)
#2575000
0(
1&
b10 ,
b110 +
1)
#2580000
0)
#2585000
0'
1%
b11 ,
b1100 +
1)
#2590000
0)
#2595000
0&
1$
b100 ,
b11000 +
1)
#2600000
0)
#2605000
0%
1#
b101 ,
b110000 +
1)
#2610000
0)
#2615000
0$
1"
b110 ,
b1100000 +
1)
#2620000
0)
#2625000
0#
1!
b111 ,
b11000000 +
1)
#2630000
0)
#2635000
0"
0*
b110000000 +
1)
#2640000
0)
#2645000
1"
b110 ,
b11000000 +
1)
#2650000
0)
#2655000
1#
0!
b101 ,
b1100000 +
1)
#2660000
0)
#2665000
1$
0"
b100 ,
b110000 +
1)
#2670000
0)
#2675000
1%
0#
b11 ,
b11000 +
1)
#2680000
0)
#2685000
1&
0$
b10 ,
b1100 +
1)
#2690000
0)
#2695000
1'
0%
b1 ,
b110 +
1)
#2700000
0)
#2705000
1(
0&
b0 ,
b11 +
1)
#2710000
0)
#2715000
0'
1*
b1 +
1)
#2720000
0)
#2725000
1'
b1 ,
b11 +
1)
#2730000
0)
#2735000
0(
1&
b10 ,
b110 +
1)
#2740000
0)
#2745000
0'
1%
b11 ,
b1100 +
1)
#2750000
0)
#2755000
0&
1$
b100 ,
b11000 +
1)
#2760000
0)
#2765000
0%
1#
b101 ,
b110000 +
1)
#2770000
0)
#2775000
0$
1"
b110 ,
b1100000 +
1)
#2780000
0)
#2785000
0#
1!
b111 ,
b11000000 +
1)
#2790000
0)
#2795000
0"
0*
b110000000 +
1)
#2800000
0)
#2805000
1"
b110 ,
b11000000 +
1)
#2810000
0)
#2815000
1#
0!
b101 ,
b1100000 +
1)
#2820000
0)
#2825000
1$
0"
b100 ,
b110000 +
1)
#2830000
0)
#2835000
1%
0#
b11 ,
b11000 +
1)
#2840000
0)
#2845000
1&
0$
b10 ,
b1100 +
1)
#2850000
0)
#2855000
1'
0%
b1 ,
b110 +
1)
#2860000
0)
#2865000
1(
0&
b0 ,
b11 +
1)
#2870000
0)
#2875000
0'
1*
b1 +
1)
#2880000
0)
#2885000
1'
b1 ,
b11 +
1)
#2890000
0)
#2895000
0(
1&
b10 ,
b110 +
1)
#2900000
0)
#2905000
0'
1%
b11 ,
b1100 +
1)
#2910000
0)
#2915000
0&
1$
b100 ,
b11000 +
1)
#2920000
0)
#2925000
0%
1#
b101 ,
b110000 +
1)
#2930000
0)
#2935000
0$
1"
b110 ,
b1100000 +
1)
#2940000
0)
#2945000
0#
1!
b111 ,
b11000000 +
1)
#2950000
0)
#2955000
0"
0*
b110000000 +
1)
#2960000
0)
#2965000
1"
b110 ,
b11000000 +
1)
#2970000
0)
#2975000
1#
0!
b101 ,
b1100000 +
1)
#2980000
0)
#2985000
1$
0"
b100 ,
b110000 +
1)
#2990000
0)
#2995000
1%
0#
b11 ,
b11000 +
1)
#3000000
0)
#3005000
1&
0$
b10 ,
b1100 +
1)
#3010000
0)
#3015000
1'
0%
b1 ,
b110 +
1)
#3020000
0)
#3025000
1(
0&
b0 ,
b11 +
1)
#3030000
0)
#3035000
0'
1*
b1 +
1)
#3040000
0)
#3045000
1'
b1 ,
b11 +
1)
#3050000
0)
#3055000
0(
1&
b10 ,
b110 +
1)
#3060000
0)
#3065000
0'
1%
b11 ,
b1100 +
1)
#3070000
0)
#3075000
0&
1$
b100 ,
b11000 +
1)
#3080000
0)
#3085000
0%
1#
b101 ,
b110000 +
1)
#3090000
0)
#3095000
0$
1"
b110 ,
b1100000 +
1)
#3100000
0)
#3105000
0#
1!
b111 ,
b11000000 +
1)
#3110000
0)
#3115000
0"
0*
b110000000 +
1)
#3120000
0)
#3125000
1"
b110 ,
b11000000 +
1)
#3130000
0)
#3135000
1#
0!
b101 ,
b1100000 +
1)
#3140000
0)
#3145000
1$
0"
b100 ,
b110000 +
1)
#3150000
0)
#3155000
1%
0#
b11 ,
b11000 +
1)
#3160000
0)
#3165000
1&
0$
b10 ,
b1100 +
1)
#3170000
0)
#3175000
1'
0%
b1 ,
b110 +
1)
#3180000
0)
#3185000
1(
0&
b0 ,
b11 +
1)
#3190000
0)
#3195000
0'
1*
b1 +
1)
#3200000
0)
#3205000
1'
b1 ,
b11 +
1)
#3210000
0)
#3215000
0(
1&
b10 ,
b110 +
1)
#3220000
0)
#3225000
0'
1%
b11 ,
b1100 +
1)
#3230000
0)
#3235000
0&
1$
b100 ,
b11000 +
1)
#3240000
0)
#3245000
0%
1#
b101 ,
b110000 +
1)
#3250000
0)
#3255000
0$
1"
b110 ,
b1100000 +
1)
#3260000
0)
#3265000
0#
1!
b111 ,
b11000000 +
1)
#3270000
0)
#3275000
0"
0*
b110000000 +
1)
#3280000
0)
#3285000
1"
b110 ,
b11000000 +
1)
#3290000
0)
#3295000
1#
0!
b101 ,
b1100000 +
1)
#3300000
0)
#3305000
1$
0"
b100 ,
b110000 +
1)
#3310000
0)
#3315000
1%
0#
b11 ,
b11000 +
1)
#3320000
0)
#3325000
1&
0$
b10 ,
b1100 +
1)
#3330000
0)
#3335000
1'
0%
b1 ,
b110 +
1)
#3340000
0)
#3345000
1(
0&
b0 ,
b11 +
1)
#3350000
0)
#3355000
0'
1*
b1 +
1)
#3360000
0)
#3365000
1'
b1 ,
b11 +
1)
#3370000
0)
#3375000
0(
1&
b10 ,
b110 +
1)
#3380000
0)
#3385000
0'
1%
b11 ,
b1100 +
1)
#3390000
0)
#3395000
0&
1$
b100 ,
b11000 +
1)
#3400000
0)
#3405000
0%
1#
b101 ,
b110000 +
1)
#3410000
0)
#3415000
0$
1"
b110 ,
b1100000 +
1)
#3420000
0)
#3425000
0#
1!
b111 ,
b11000000 +
1)
#3430000
0)
#3435000
0"
0*
b110000000 +
1)
#3440000
0)
#3445000
1"
b110 ,
b11000000 +
1)
#3450000
0)
#3455000
1#
0!
b101 ,
b1100000 +
1)
#3460000
0)
#3465000
1$
0"
b100 ,
b110000 +
1)
#3470000
0)
#3475000
1%
0#
b11 ,
b11000 +
1)
#3480000
0)
#3485000
1&
0$
b10 ,
b1100 +
1)
#3490000
0)
#3495000
1'
0%
b1 ,
b110 +
1)
#3500000
0)
#3505000
1(
0&
b0 ,
b11 +
1)
#3510000
0)
#3515000
0'
1*
b1 +
1)
#3520000
0)
#3525000
1'
b1 ,
b11 +
1)
#3530000
0)
#3535000
0(
1&
b10 ,
b110 +
1)
#3540000
0)
#3545000
0'
1%
b11 ,
b1100 +
1)
#3550000
0)
#3555000
0&
1$
b100 ,
b11000 +
1)
#3560000
0)
#3565000
0%
1#
b101 ,
b110000 +
1)
#3570000
0)
#3575000
0$
1"
b110 ,
b1100000 +
1)
#3580000
0)
#3585000
0#
1!
b111 ,
b11000000 +
1)
#3590000
0)
#3595000
0"
0*
b110000000 +
1)
#3600000
0)
#3605000
1"
b110 ,
b11000000 +
1)
#3610000
0)
#3615000
1#
0!
b101 ,
b1100000 +
1)
#3620000
0)
#3625000
1$
0"
b100 ,
b110000 +
1)
#3630000
0)
#3635000
1%
0#
b11 ,
b11000 +
1)
#3640000
0)
#3645000
1&
0$
b10 ,
b1100 +
1)
#3650000
0)
#3655000
1'
0%
b1 ,
b110 +
1)
#3660000
0)
#3665000
1(
0&
b0 ,
b11 +
1)
#3670000
0)
#3675000
0'
1*
b1 +
1)
#3680000
0)
#3685000
1'
b1 ,
b11 +
1)
#3690000
0)
#3695000
0(
1&
b10 ,
b110 +
1)
#3700000
0)
#3705000
0'
1%
b11 ,
b1100 +
1)
#3710000
0)
#3715000
0&
1$
b100 ,
b11000 +
1)
#3720000
0)
#3725000
0%
1#
b101 ,
b110000 +
1)
#3730000
0)
#3735000
0$
1"
b110 ,
b1100000 +
1)
#3740000
0)
#3745000
0#
1!
b111 ,
b11000000 +
1)
#3750000
0)
#3755000
0"
0*
b110000000 +
1)
#3760000
0)
#3765000
1"
b110 ,
b11000000 +
1)
#3770000
0)
#3775000
1#
0!
b101 ,
b1100000 +
1)
#3780000
0)
#3785000
1$
0"
b100 ,
b110000 +
1)
#3790000
0)
#3795000
1%
0#
b11 ,
b11000 +
1)
#3800000
0)
#3805000
1&
0$
b10 ,
b1100 +
1)
#3810000
0)
#3815000
1'
0%
b1 ,
b110 +
1)
#3820000
0)
#3825000
1(
0&
b0 ,
b11 +
1)
#3830000
0)
#3835000
0'
1*
b1 +
1)
#3840000
0)
#3845000
1'
b1 ,
b11 +
1)
#3850000
0)
#3855000
0(
1&
b10 ,
b110 +
1)
#3860000
0)
#3865000
0'
1%
b11 ,
b1100 +
1)
#3870000
0)
#3875000
0&
1$
b100 ,
b11000 +
1)
#3880000
0)
#3885000
0%
1#
b101 ,
b110000 +
1)
#3890000
0)
#3895000
0$
1"
b110 ,
b1100000 +
1)
#3900000
0)
#3905000
0#
1!
b111 ,
b11000000 +
1)
#3910000
0)
#3915000
0"
0*
b110000000 +
1)
#3920000
0)
#3925000
1"
b110 ,
b11000000 +
1)
#3930000
0)
#3935000
1#
0!
b101 ,
b1100000 +
1)
#3940000
0)
#3945000
1$
0"
b100 ,
b110000 +
1)
#3950000
0)
#3955000
1%
0#
b11 ,
b11000 +
1)
#3960000
0)
#3965000
1&
0$
b10 ,
b1100 +
1)
#3970000
0)
#3975000
1'
0%
b1 ,
b110 +
1)
#3980000
0)
#3985000
1(
0&
b0 ,
b11 +
1)
#3990000
0)
#3995000
0'
1*
b1 +
1)
#4000000
0)
#4005000
1'
b1 ,
b11 +
1)
#4010000
0)
#4015000
0(
1&
b10 ,
b110 +
1)
#4020000
0)
#4025000
0'
1%
b11 ,
b1100 +
1)
#4030000
0)
